g4fp/__init__.py
g4fp/g4fp.py
g4fp-1.2.3.dist-info/LICENSE.txt
g4fp-1.2.3.dist-info/METADATA
g4fp-1.2.3.dist-info/WHEEL
g4fp-1.2.3.dist-info/top_level.txt
g4fp-1.2.3.dist-info/RECORD
