Metadata-Version: 2.1
Name: g4fp
Version: 1.2.3
Summary: A library for unlimited use of LLM through g4f, using a proxy
Home-page: https://github.com/Leolox228/g4fp
Author: Leonid
Author-email: leo.gladkikh2@gmail.com
License: GPL-3.0
Classifier: Programming Language :: Python :: 3
Classifier: License :: OSI Approved :: GNU General Public License v3 (GPLv3)
Classifier: Operating System :: OS Independent
Requires-Python: >=3.7
License-File: LICENSE.txt
Requires-Dist: g4f
